screentime/__init__.py
screentime/__version__.py
screentime/screentime.py
screentime-0.0.1.dist-info/LICENSE
screentime-0.0.1.dist-info/METADATA
screentime-0.0.1.dist-info/WHEEL
screentime-0.0.1.dist-info/entry_points.txt
screentime-0.0.1.dist-info/top_level.txt
screentime-0.0.1.dist-info/RECORD
