Metadata-Version: 2.1
Name: screentime
Version: 0.0.1
Summary: ScreenTime™ for non iOS devices
Home-page: https://github.com/danieloconell/screentime
Author: Daniel O'Connell
Author-email: dan.ben.oconnell@gmail.com
License: UNKNOWN
Platform: UNKNOWN
Classifier: Programming Language :: Python :: 3
Classifier: License :: OSI Approved :: MIT License
Classifier: Operating System :: OS Independent
